{
    "articles": [
        {
            "STOCK_ID": "0070",
            "TITLE": "[標的] 00708L黃金正二-可以進嗎?",
            "ID": "M.1744538593.A.7AD",
            "LINK": "https://www.ptt.cc/bbs/Stock/M.1744538593.A.7AD.html",
            "AUTHOR": "kokoko0707",
            "CONTENT": "作者kokoko0707 (潛水攻城師)看板Stock標題[標的] 00708L黃金正二-可以進嗎?時間Sun Apr 13 18:03:11 2025\n標的：\n00708L 黃金正二\n\n分類：多/空/討論/心得\n上週股、債、黃金都崩\n尤其黃金上周崩那一根嚇死人，然後就垂直起飛\n黃金不是看好嗎? 金融危機不就大家會搶黃金嗎? 為何會崩那一大根再垂直起飛?\n\n明天想要追黃金正二，大家看好嗎?\n反正股票已經變賭場了，半導體關稅應該也跟黃金無關\n債最近崩了，黃金看起來比較像無腦多，覺得可以進嗎?\n\n假如美股再開始崩，黃金還會跟著崩嗎?\n\n--\n",
            "TIME": "Sun Apr 13 18:03:11 2025",
            "MESSAGE_ALL": 111,
            "BOO": 4,
            "PUSH": 46,
            "MESSAGE_COUNT": 42,
            "NEUTRAL": 61,
            "TAG": "標的"
        },
        {
            "STOCK_ID": "0200",
            "TITLE": "[標的] 02001L 蘋果正2 多到爆",
            "ID": "M.1744527962.A.0CA",
            "LINK": "https://www.ptt.cc/bbs/Stock/M.1744527962.A.0CA.html",
            "AUTHOR": "cailon",
            "CONTENT": "作者cailon (我不一定是我!)看板Stock標題[標的] 02001L 蘋果正2時間Sun Apr 13 15:06:00 2025\n想問一下\n\n像阿肥這種飛米小戶（比奈米還小）\n\n買這種標的可以嗎？\n\n沒錢可以買美股\n\n或者開海外帳戶\n\n聽說蘋果要起飛了\n\n買這種正2可以嗎？\n\n阿肥也想讓川普大大帶著飛\n\n損：買的話就20%出掉好了\n\n利：看能不能回到前波高點\n\n阿肥會努力賺本金的！\n\n喔還沒進場所以沒有單\n\n有進場一定會貼單\n\n\n--\n",
            "TIME": "Sun Apr 13 15:06:00 2025",
            "MESSAGE_ALL": 25,
            "BOO": 1,
            "PUSH": 13,
            "MESSAGE_COUNT": 12,
            "NEUTRAL": 11,
            "TAG": "標的"
        },
        {
            "STOCK_ID": "0200",
            "TITLE": "Re: [標的] 02001L 蘋果正2",
            "ID": "M.1744542216.A.EEB",
            "LINK": "https://www.ptt.cc/bbs/Stock/M.1744542216.A.EEB.html",
            "AUTHOR": "johnyang",
            "CONTENT": "作者johnyang (Saico)看板Stock標題Re: [標的] 02001L 蘋果正2時間Sun Apr 13 19:03:33 2025\n簡單回覆提醒\n\n看名字買商品是很危險的\n02001L蘋果正二\n官方DM網頁連結如下\nhttps://www.fubon.com/securities/hot_new/ETN/ETN02001LR/\n\n指數名稱\n「富邦特選大蘋果報酬指數」\n\n成分股\n蘋果公司(Apple.US)最近公布供應商名單中篩選符合｢流動性」及｢財務穩健」二大指標，且\n以自由流通市值排序之前十大個股，「富邦特選大蘋果報酬指數」最能表彰臺灣大型蘋果供\n應鏈公司之投資績效表現。\n\n https://i.imgur.com/pWLrTCF.jpeg\n（僅供參考 非最新持股）\n\n所以這支與AAPL沒有直接關聯喔\n基本上是跟著台股十間公司走\n另外這是ETN\n無追蹤誤差 有到期日\n最大風險是券商違約（富邦金機率低）\n\n※ 引述《cailon》之銘言\n: 想問一下\n: 像阿肥這種飛米小戶（比奈米還小）\n: 買這種標的可以嗎？\n: 沒錢可以買美股\n: 或者開海外帳戶\n: 聽說蘋果要起飛了\n: 買這種正2可以嗎？\n: 阿肥也想讓川普大大帶著飛\n: 損：買的話就20%出掉好了\n: 利：看能不能回到前波高點\n: 阿肥會努力賺本金的！\n: 喔還沒進場所以沒有單\n: 有進場一定會貼單\n----\nSent from BePTT\n\n--\n",
            "TIME": "Sun Apr 13 19:03:33 2025",
            "MESSAGE_ALL": 10,
            "BOO": 0,
            "PUSH": 8,
            "MESSAGE_COUNT": 8,
            "NEUTRAL": 2,
            "TAG": "Re標的"
        },
        {
            "STOCK_ID": "2317",
            "TITLE": "Re: [標的] 2317 鴻海",
            "ID": "M.1744509384.A.4ED",
            "LINK": "https://www.ptt.cc/bbs/Stock/M.1744509384.A.4ED.html",
            "AUTHOR": "leowang1027",
            "CONTENT": "作者leowang1027 (無)看板Stock標題Re: [標的] 2317 鴻海時間Sun Apr 13 09:56:22 2025\n恕刪\n\n   這個週末川普一連串簽署關於中國產業鏈的豁免條款，包含電腦，手機，各類半導體相關，幾乎就是等於在告訴你果鏈獲得赦免，哪怕中國出場，相對於半島體川普要特別拉出來做單獨課稅的不確定性，鴻海根本完全是安全的範圍，畢竟它跟果鏈的牽扯太深，所以現在可以說，公公已經準備得到大救贖了嗎？ 沒意外應該要爆噴好幾天！\n\n--\nSent from nPTT on my iPhone 14\n\n--\n",
            "TIME": "Sun Apr 13 09:56:22 2025",
            "MESSAGE_ALL": 103,
            "BOO": 10,
            "PUSH": 54,
            "MESSAGE_COUNT": 44,
            "NEUTRAL": 39,
            "TAG": "Re標的"
        },
        {
            "STOCK_ID": "0070",
            "TITLE": "Re: [標的] 00708L黃金正二-可以進嗎?",
            "ID": "M.1744542691.A.9F3",
            "LINK": "https://www.ptt.cc/bbs/Stock/M.1744542691.A.9F3.html",
            "AUTHOR": "Jefferay",
            "CONTENT": "作者Jefferay (中華民國，千秋萬世)看板Stock標題Re: [標的] 00708L黃金正二-可以進嗎?時間Sun Apr 13 19:11:29 2025\n※ 引述《kokoko0707 (潛水攻城師)》之銘言：\n: 標的：\n: 00708L 黃金正二\n: 分類：多/空/討論/心得\n: 上週股、債、黃金都崩\n: 尤其黃金上周崩那一根嚇死人，然後就垂直起飛\n: 黃金不是看好嗎? 金融危機不就大家會搶黃金嗎? 為何會崩那一大根再垂直起飛?\n: 明天想要追黃金正二，大家看好嗎?\n: 反正股票已經變賭場了，半導體關稅應該也跟黃金無關\n: 債最近崩了，黃金看起來比較像無腦多，覺得可以進嗎?\n: 假如美股再開始崩，黃金還會跟著崩嗎?\n\n避險可以買黃金，但僅限實體\n\n衍伸金融商品沒避險功能\n\n因為衍伸黃金商品的發行量為實物的100倍\n\n真的要實物交割時你的紙黃金會直接歸0\n\n因此在亂世動盪時只能買黃金現貨\n\n至於你問為何上周黃金會跟股票一起跌\n\n因為基金經理人為了讓客戶贖回擠兌\n\n必須賣掉自身的黃金部位變現\n\n所以每次剛開始崩盤時黃金會先跌\n\n但之後就會飛天\n\n每次危機來臨時，大家第一反應都是賣股票\n\n而不是買黃金\n\n但值得慶幸的是，現在還不是真正的危機\n\n當真正的危機來時\n\n基金經理人是不會鳥你的贖回\n\n並直接捲款潛逃讓你找不到人\n\n\n\n\n-----\nSent from JPTT on my Samsung SM-A5460.\n\n--\n",
            "TIME": "Sun Apr 13 19:11:29 2025",
            "MESSAGE_ALL": 11,
            "BOO": 0,
            "PUSH": 7,
            "MESSAGE_COUNT": 7,
            "NEUTRAL": 4,
            "TAG": "Re標的"
        },
        {
            "STOCK_ID": "2317",
            "TITLE": "Re: [標的] 2317 鴻海",
            "ID": "M.1744519000.A.C15",
            "LINK": "https://www.ptt.cc/bbs/Stock/M.1744519000.A.C15.html",
            "AUTHOR": "xname",
            "CONTENT": "作者xname (天涯浪跡客)看板Stock標題Re: [標的] 2317 鴻海時間Sun Apr 13 12:36:38 2025\n※ 引述《leowang1027 (無)》之銘言：\n: 恕刪\n:    這個週末川普一連串簽署關於中國產業鏈的豁免條款，包含電腦，手機，各類半導體相關，\n:    幾乎就是等於在告訴你果鏈獲得赦免，哪怕中國出場，相對於半島體川普要特別拉出來做單獨課稅的不確定性，\n:    鴻海根本完全是安全的範圍，畢竟它跟果鏈的牽扯太深，所以現在可以說，公公已經準備得到大救贖了嗎？\n:    沒意外應該要爆噴好幾天！\n\n  上述是對鴻海有利的消息面，不過可以先看看上週的集保分布狀況\n\n        https://i.imgur.com/qZDTmvz.png\n\n圖中的綠線是累積人數的 PR90，黑線是所有股東 PR99 的位置，這周鴻海股價走勢很精采，一開始連三天跌停，\n\n而週二、週三是盤中跌停，這兩日成交張數分別是 30.8萬張，36.6萬張，這麼大的成交量，從集保的分布來看，\n\n可以合理推估是 PR99 以上的中實戶因為融資或質押斷頭賣出，十張以下 PR90 的小散戶和五十張以下(PR90~PR99)\n\n的小資族進場撿便宜，呈現了中實戶恐懼賣出，小散戶、小資族貪婪買進的狀況。\n\n現在中實戶和千張大戶已經賣出手中持股，被關稅大帝逼出場外觀望，後續股價會不會爆噴，牽涉已經買票入場，\n\n承擔關稅大帝威壓的小散戶和小資族能把手中的股票捏的多緊。\n\n鴻海 2025Q1 營收年增 24.2%，已買到低價的鴻海股東，或許可以等下個月開獎的 2025Q1 財報來決定手中股票的去留。\n\n--\n",
            "TIME": "Sun Apr 13 12:36:38 2025",
            "MESSAGE_ALL": 27,
            "BOO": 0,
            "PUSH": 10,
            "MESSAGE_COUNT": 10,
            "NEUTRAL": 17,
            "TAG": "Re標的"
        },
        {
            "STOCK_ID": "2317",
            "TITLE": "Re: [標的] 2317 鴻海",
            "ID": "M.1744544578.A.49A",
            "LINK": "https://www.ptt.cc/bbs/Stock/M.1744544578.A.49A.html",
            "AUTHOR": "vatog",
            "CONTENT": "作者vatog (...)看板Stock標題Re: [標的] 2317 鴻海時間Sun Apr 13 19:42:56 2025\n※ 引述《leowang1027 (無)》之銘言：\n: 恕刪\n:    這個週末川普一連串簽署關於中國產業鏈的豁免條款，包含電腦，手機，各類半導體相關，幾乎就是等於在告訴你果鏈獲得赦免，哪怕中國出場，相對於半島體川普要特別拉出來做單獨課稅的不確定性，鴻海根本完全是安全的範圍，畢竟它跟果鏈的牽扯太深，所以現在可以說，公公已經準備得到大救贖了嗎？ 沒意外應該要爆噴好幾天！\n\nhttps://uanalyze.com.tw/articles/5251314489\n備份: https://imgur.com/a/2025-4-13-5O7K2z0\n根據這裡的投影片(假設為真)，智能手機/手錶，大部分的雲端網路產品、\n電腦終端產品得到豁免，不用吃125%關稅。\n\n但有一些例外:\n藍芽音箱\n無線耳機\n智慧音樂揚聲器\n電視機\n遊戲機\n手機主板/手錶主板\n智慧音樂揚聲器主板\n手機零件/手錶零件/無線耳機零件\n智慧音樂揚聲器零件\n伺服器機櫃\nPCB板\n數據線\n\n以上還是要吃125%額外關稅\n這些東西應該只佔鴻海營收小部份的比例，倒是可以關注主力在中國\n生產這些產品的公司\n\n\n--\n",
            "TIME": "Sun Apr 13 19:42:56 2025",
            "MESSAGE_ALL": 76,
            "BOO": 0,
            "PUSH": 40,
            "MESSAGE_COUNT": 40,
            "NEUTRAL": 36,
            "TAG": "Re標的"
        },
        {
            "STOCK_ID": "2208",
            "TITLE": "[標的] 2208台船 鍵盤多",
            "ID": "M.1744546948.A.E47",
            "LINK": "https://www.ptt.cc/bbs/Stock/M.1744546948.A.E47.html",
            "AUTHOR": "komengtu",
            "CONTENT": "作者komengtu (Meng)看板Stock標題[標的] 2208台船 鍵盤多時間Sun Apr 13 20:22:15 2025\n標的：\n\n2208 台船\n\n分類：多/空/討論/心得\n\n鍵盤多單\n\n分析/正文：\n\n技術分析打底完成，基本面看起來很爛，看不懂在漲什麼\n\n進退場機制：\n\n預計納入虛擬市場的投資組合，觸及25元分批停利\n\n--\n",
            "TIME": "Sun Apr 13 20:22:15 2025",
            "MESSAGE_ALL": 27,
            "BOO": 2,
            "PUSH": 9,
            "MESSAGE_COUNT": 7,
            "NEUTRAL": 16,
            "TAG": "標的"
        }
    ]
}